docrouter/__init__.py
docrouter/py.typed
docrouter/tools.py
docrouter-0.2.1.dist-info/METADATA
docrouter-0.2.1.dist-info/WHEEL
docrouter-0.2.1.dist-info/RECORD
