Metadata-Version: 2.4
Name: docrouter
Version: 0.2.1
Summary: Unified document interrogation: retrieve, screenshot, search
License: MIT
Keywords: document,docx,extraction,pdf,pptx,search
Classifier: Development Status :: 3 - Alpha
Classifier: Intended Audience :: Developers
Classifier: License :: OSI Approved :: MIT License
Classifier: Programming Language :: Python :: 3.10
Classifier: Programming Language :: Python :: 3.11
Classifier: Programming Language :: Python :: 3.12
Requires-Python: >=3.10
Provides-Extra: all
Requires-Dist: beautifulsoup4>=4.12; extra == 'all'
Requires-Dist: lxml>=5.0; extra == 'all'
Requires-Dist: markdown-it-py>=3.0; extra == 'all'
Requires-Dist: pymupdf>=1.24; extra == 'all'
Requires-Dist: python-docx>=1.1; extra == 'all'
Requires-Dist: python-pptx>=0.6; extra == 'all'
Provides-Extra: dev
Requires-Dist: pytest>=8.0; extra == 'dev'
Provides-Extra: docx
Requires-Dist: python-docx>=1.1; extra == 'docx'
Provides-Extra: html
Requires-Dist: beautifulsoup4>=4.12; extra == 'html'
Requires-Dist: lxml>=5.0; extra == 'html'
Provides-Extra: md
Requires-Dist: markdown-it-py>=3.0; extra == 'md'
Provides-Extra: pdf
Requires-Dist: pymupdf>=1.24; extra == 'pdf'
Provides-Extra: pptx
Requires-Dist: python-pptx>=0.6; extra == 'pptx'
